 {
    "Europe": {
        "name": "Modern Europe",
        "path": "TMCW",
        "genre": "20'th Century Games",
        "production": false,
        "fileName": "\\Wargame\\ModernBattles\\Europe\\Europe",
        "description":"",
        "params":{
        },
        "scenarios": {
            "main": {
                "name": "main",
                "description": "original game.",
                "supply": true,
                "longDescription": "6 turns"
            },
            "three": {
                "name": "three",
                "description": "Scenario 3",
                "longDescription": "12 turms"
            },
            "four": {
                "name": "four",
                "description": "Scenario 4",
                "longDescription": "10 turns"
            }
        }
    },
     "Bulge": {
         "name": "Battle of the Bulge",
         "path": "TMCW",
         "genre": "20'th Century Games",
         "production": false,
         "fileName": "\\Wargame\\ModernBattles\\Bulge\\Bulge",
         "description":"",
         "params":{
         },
         "scenarios": {
             "one": {
                 "name": "one",
                 "description": "scenario one.",
                 "supply": true,
                 "longDescription": "7 turns"
             }
         }
     }

 }